hello_rye/__init__.py
hello_rye-0.2.0.dist-info/METADATA
hello_rye-0.2.0.dist-info/WHEEL
hello_rye-0.2.0.dist-info/RECORD
